jnpr_pathfinder_mcp/__init__.py
jnpr_pathfinder_mcp/__main__.py
jnpr_pathfinder_mcp/helpers.py
jnpr_pathfinder_mcp/server/__init__.py
jnpr_pathfinder_mcp/server/cli_explorer.py
jnpr_pathfinder_mcp/server/feature_explorer.py
jnpr_pathfinder_mcp/server/hct.py
jnpr_pathfinder_mcp/server/pathfinder.py
jnpr_pathfinder_mcp-0.2.0.dist-info/WHEEL
jnpr_pathfinder_mcp-0.2.0.dist-info/entry_points.txt
jnpr_pathfinder_mcp-0.2.0.dist-info/METADATA
jnpr_pathfinder_mcp-0.2.0.dist-info/RECORD
