Metadata-Version: 2.3
Name: jnpr-pathfinder-mcp
Version: 0.2.0
Summary: An MCP Server for interacting with Juniper's public Pathfinder APIs (https://apps.juniper.net).
Author: cbinckly
Author-email: cbinckly <cbinckly@gmail.com>
Requires-Dist: bs4>=0.0.2
Requires-Dist: fastmcp>=2.12.4
Requires-Dist: pydantic>=2.11.10
Requires-Dist: requests>=2.32.5
Requires-Python: >=3.11
